pysimstudy/__init__.py
pysimstudy/add_correlated_data.py
pysimstudy/add_data.py
pysimstudy/asserts.py
pysimstudy/define_data.py
pysimstudy/generate_correlated_data.py
pysimstudy/generate_data.py
pysimstudy/generate_dist.py
pysimstudy/group_data.py
pysimstudy/utility.py
pysimstudy-0.0.93.dist-info/LICENSE
pysimstudy-0.0.93.dist-info/METADATA
pysimstudy-0.0.93.dist-info/WHEEL
pysimstudy-0.0.93.dist-info/top_level.txt
pysimstudy-0.0.93.dist-info/RECORD
