Metadata-Version: 2.1
Name: pysimstudy
Version: 0.0.93
Summary: A package for synthetic data generation
Author-email: Keith Goldfeld <keith.goldfeld@nyumc.org>, Gabriel Gilling <gabrielgilling@ibm.com>, David Cruz <d.cruz@ibm.com>, Jordan Bond <jbond@ibm.com>
Project-URL: Homepage, https://github.com/DAVIDCRUZ0202/pysimstudy
Project-URL: Bug Tracker, https://github.com/DAVIDCRUZ0202/pysimstudy/issues
Classifier: Programming Language :: Python :: 3
Classifier: License :: OSI Approved :: GNU Lesser General Public License v3 (LGPLv3)
Classifier: Operating System :: OS Independent
Requires-Python: >=3.7
License-File: LICENSE
Requires-Dist: pandas (==1.2.4)
Requires-Dist: numpy (==1.20.2)
Requires-Dist: scipy (==1.7.3)
Requires-Dist: simpleeval (==0.9.12)
Requires-Dist: patsy (==0.5.1)
